sp_cetesb_divadmin/__init__.py
sp_cetesb_divadmin/lyr.py
sp_cetesb_divadmin/data/__init__.py
sp_cetesb_divadmin/data/output/geo/sp_cetesb.7z
sp_cetesb_divadmin/data/output/tab/tab_cetesb_agencias.csv
sp_cetesb_divadmin/data/output/tab/tab_cetesb_municipios.csv
sp_cetesb_divadmin-0.0.5.dist-info/LICENSE
sp_cetesb_divadmin-0.0.5.dist-info/METADATA
sp_cetesb_divadmin-0.0.5.dist-info/WHEEL
sp_cetesb_divadmin-0.0.5.dist-info/top_level.txt
sp_cetesb_divadmin-0.0.5.dist-info/RECORD
