Metadata-Version: 2.1
Name: sp-cetesb-divadmin
Version: 0.0.5
Summary: Dados Espaciais da Divisão Administrativa da CETESB, por meio de suas Agências Ambientais
Home-page: https://github.com/open-geodata/sp_cetesb_divadmin
Author: Michel Metran
Author-email: michelmetran@gmail.com
Keywords: python,dados espaciais,geoprocessamento
Classifier: Programming Language :: Python :: 3
Classifier: License :: OSI Approved :: MIT License
Classifier: Operating System :: OS Independent
Classifier: Natural Language :: Portuguese
Classifier: Intended Audience :: Developers
Requires-Python: >=3
License-File: LICENSE
